{"cameraMode":{"drawMode":0,"name":"Shaded","section":"Shading Mode"},"sceneLighting":true,"audioPlay":false,"sceneViewState":{"m_AlwaysRefresh":false,"showFog":true,"showSkybox":true,"showFlares":true,"showImageEffects":true,"showParticleSystems":true,"showVisualEffectGraphs":true,"m_FxEnabled":true},"in2DMode":false,"pivot":{"x":450.8731994628906,"y":708.4462890625,"z":-15.664194107055664},"rotation":{"x":-0.17874054610729218,"y":0.6906076073646545,"z":-0.18251097202301026,"w":-0.6766872406005859},"size":10.0,"orthographic":false}